django_ltree/__init__.py
django_ltree/apps.py
django_ltree/checks.py
django_ltree/fields.py
django_ltree/functions.py
django_ltree/lookups.py
django_ltree/managers.py
django_ltree/migrations/0001_create_extension.py
django_ltree/migrations/__init__.py
django_ltree/models.py
django_ltree/paths.py
django_ltree/querysets.py
django_ltree_2-0.1.12.dist-info/LICENSE
django_ltree_2-0.1.12.dist-info/METADATA
django_ltree_2-0.1.12.dist-info/WHEEL
django_ltree_2-0.1.12.dist-info/RECORD
