Metadata-Version: 2.3
Name: django-ltree-2
Version: 0.1.12
Summary: Continual of django-ltree with additional goodies
License: MIT
Author: baseplate-admin
Author-email: 61817579+baseplate-admin@users.noreply.github.com
Maintainer: baseplate-admin
Maintainer-email: 61817579+baseplate-admin@users.noreply.github.com
Requires-Python: >=3.9
Classifier: Development Status :: 5 - Production/Stable
Classifier: Framework :: Django
Classifier: Framework :: Django :: 4.2
Classifier: Framework :: Django :: 5.0
Classifier: Framework :: Django :: 5.1
Classifier: Intended Audience :: Developers
Classifier: License :: OSI Approved :: MIT License
Classifier: Operating System :: OS Independent
Classifier: Programming Language :: Python
Classifier: Programming Language :: Python :: 3
Classifier: Programming Language :: Python :: 3.9
Classifier: Programming Language :: Python :: 3.10
Classifier: Programming Language :: Python :: 3.11
Classifier: Programming Language :: Python :: 3.12
Classifier: Programming Language :: Python :: 3.13
Classifier: Programming Language :: Python :: 3.14
Classifier: Programming Language :: Python :: Implementation :: PyPy
Requires-Dist: django (>=3.2)
Requires-Dist: psycopg (>=3)
Project-URL: Bug Tracker, https://github.com/baseplate-admin/django-ltree-2/issues
Project-URL: homepage, https://github.com/baseplate-admin/django-ltree-2
Project-URL: repository, https://github.com/baseplate-admin/django-ltree-2
